odoo/addons/calendar_partner_color/README.rst
odoo/addons/calendar_partner_color/__init__.py
odoo/addons/calendar_partner_color/__manifest__.py
odoo/addons/calendar_partner_color/hooks.py
odoo/addons/calendar_partner_color/i18n/calendar_partner_color.pot
odoo/addons/calendar_partner_color/models/__init__.py
odoo/addons/calendar_partner_color/models/calendar_event.py
odoo/addons/calendar_partner_color/models/res_partner.py
odoo/addons/calendar_partner_color/readme/CONFIGURE.rst
odoo/addons/calendar_partner_color/readme/CONTRIBUTORS.rst
odoo/addons/calendar_partner_color/readme/DESCRIPTION.rst
odoo/addons/calendar_partner_color/static/description/icon.png
odoo/addons/calendar_partner_color/static/description/index.html
odoo/addons/calendar_partner_color/views/calendar_event.xml
odoo/addons/calendar_partner_color/views/partner.xml
odoo14_addon_calendar_partner_color-14.0.0.1.0.dist-info/METADATA
odoo14_addon_calendar_partner_color-14.0.0.1.0.dist-info/WHEEL
odoo14_addon_calendar_partner_color-14.0.0.1.0.dist-info/top_level.txt
odoo14_addon_calendar_partner_color-14.0.0.1.0.dist-info/RECORD
